{
  "last_updated": "2026-02-19T01:05:57.089634+00:00",
  "total_monkeys": 33,
  "active_today": 12,
  "generations": {
    "1": 14,
    "2": 19
  },
  "avg_rarity": 24.6,
  "max_rarity": 46.67,
  "min_rarity": 10.0,
  "rarest_trait": {
    "trait": "background",
    "value": "mountains",
    "count": 1
  },
  "most_common_trait": {
    "trait": "special",
    "value": "none",
    "count": 21
  },
  "trait_distribution": {
    "body_color": {
      "crystal": 3,
      "gray": 2,
      "tan": 7,
      "genesis_gold": 2,
      "beige": 3,
      "silver": 3,
      "bronze": 2,
      "prismatic": 1,
      "copper": 1,
      "green": 1,
      "purple": 1,
      "golden": 2,
      "brown": 2,
      "holographic": 2,
      "blue": 1
    },
    "face_expression": {
      "happy": 4,
      "excited": 3,
      "cool": 3,
      "neutral": 6,
      "curious": 3,
      "legendary": 1,
      "cosmic": 1,
      "sleepy": 2,
      "mischievous": 2,
      "laughing": 1,
      "enlightened": 1,
      "zen": 1,
      "surprised": 3,
      "wise": 1,
      "winking": 1
    },
    "accessory": {
      "bandana": 7,
      "bow": 2,
      "none": 7,
      "simple_hat": 4,
      "jetpack": 2,
      "sunglasses": 1,
      "wings": 1,
      "laser_eyes": 2,
      "headphones": 2,
      "monocle": 2,
      "crown": 2,
      "golden_crown": 1
    },
    "pattern": {
      "spots": 4,
      "diamonds": 4,
      "stripes": 5,
      "gradient": 6,
      "swirls": 4,
      "cosmic_dust": 1,
      "stars": 4,
      "solid": 2,
      "lightning": 1,
      "hearts": 2
    },
    "background": {
      "white": 4,
      "blue_sky": 3,
      "space": 2,
      "green_grass": 7,
      "volcano": 3,
      "sunset": 7,
      "beach": 4,
      "forest": 1,
      "underwater": 1,
      "mountains": 1
    },
    "special": {
      "none": 21,
      "godlike": 1,
      "shadow": 4,
      "energy": 2,
      "glow": 2,
      "sparkles": 2,
      "aura": 1
    }
  }
}